pyreo/__init__.py
pyreo/decorators.py
pyreo/mapper.py
pyreo/redis_object.py
pyreo/transactional.py
pyreo-0.0.0.dist-info/METADATA
pyreo-0.0.0.dist-info/WHEEL
pyreo-0.0.0.dist-info/top_level.txt
pyreo-0.0.0.dist-info/RECORD
