Metadata-Version: 2.1
Name: pyreo
Version: 0.0.0
Summary: UNKNOWN
Home-page: https://github.com/thomasmatecki/pyreo
Author: Thomas Matecki
Author-email: thomas.matecki@gmail.com
License: UNKNOWN
Platform: UNKNOWN
Classifier: Programming Language :: Python :: 3
Classifier: License :: OSI Approved :: MIT License
Classifier: Operating System :: OS Independent
Requires-Python: >=3.6
Requires-Dist: redis
